persianholiday/__init__.py
persianholiday/core.py
persianholiday/utils.py
persianholiday-0.0.1.dist-info/LICENSE
persianholiday-0.0.1.dist-info/METADATA
persianholiday-0.0.1.dist-info/WHEEL
persianholiday-0.0.1.dist-info/top_level.txt
persianholiday-0.0.1.dist-info/RECORD
