Metadata-Version: 2.1
Name: persianholiday
Version: 0.0.1
Summary: Get Holidays from time.ir
Home-page: https://github.com/algobits/irholiday
Author: Saman Jalinous
Author-email: saman.jalinous@gmail.com
License: UNKNOWN
Project-URL: Bug Tracker, https://github.com/algobits/irholiday/issues
Platform: UNKNOWN
Classifier: Programming Language :: Python :: 3
Classifier: License :: OSI Approved :: MIT License
Classifier: Operating System :: OS Independent
Requires-Python: >=3.6
License-File: LICENSE
Requires-Dist: requests
Requires-Dist: pandas
Requires-Dist: jdatetime
Requires-Dist: convert-numbers
Requires-Dist: beautifulsoup4
